ddp/__init__.py
ddp/connection.py
ddp/error.py
ddp/packet.py
ddp/protocol/__init__.py
ddp/protocol/header.py
ddp/protocol/id.py
ddp/protocol/message.py
ddp/protocol/packet_type.py
ddp/protocol/pixel_config.py
ddp/protocol/timecode.py
python_led_ddp-1.0.1.dist-info/METADATA
python_led_ddp-1.0.1.dist-info/WHEEL
python_led_ddp-1.0.1.dist-info/top_level.txt
python_led_ddp-1.0.1.dist-info/RECORD
