Metadata-Version: 2.4
Name: python-led-ddp
Version: 1.0.1
Summary: Distributed Display Protocol (DDP) implementation in Python
Author: Paul Fornage, Claude
License: MIT
Project-URL: Homepage, https://github.com/paul-fornage/python-led-ddp
Project-URL: Documentation, https://github.com/paul-fornage/python-led-ddp
Project-URL: Repository, https://github.com/paul-fornage/python-led-ddp
Keywords: distributed,display,protocol,ddp,pixel,led,wled
Classifier: Development Status :: 4 - Beta
Classifier: Intended Audience :: Developers
Classifier: License :: OSI Approved :: MIT License
Classifier: Programming Language :: Python :: 3
Classifier: Programming Language :: Python :: 3.10
Classifier: Programming Language :: Python :: 3.11
Classifier: Programming Language :: Python :: 3.12
Classifier: Topic :: System :: Networking
Classifier: Topic :: Multimedia
Requires-Python: >=3.10
Provides-Extra: dev
Requires-Dist: pytest>=7.0; extra == "dev"
Requires-Dist: pytest-asyncio>=0.21.0; extra == "dev"
